{
  "minMuleVersion": "3.5.0",
  "requiresEntitlement": false,
  "requiresEnterpriseLicense": false,
  "configs": [
    {
      "configElementName": "config",
      "attributes": [
        {
          "javaTypeName": "String",
          "fullQualifiedJavaTypeName": "java.lang.String",
          "isOptional": false,
          "isRefOnly": false,
          "isPayload": false,
          "isComplexType": false,
          "isEnum": false,
          "isString": true,
          "typeMirror": "java.lang.String",
          "isHttpCallback": false,
          "isArrayOrListOrMap": false,
          "javaName": "host"
        },
        {
          "javaTypeName": "String",
          "fullQualifiedJavaTypeName": "java.lang.String",
          "isOptional": false,
          "isRefOnly": false,
          "isPayload": false,
          "isComplexType": false,
          "isEnum": false,
          "isString": true,
          "typeMirror": "java.lang.String",
          "isHttpCallback": false,
          "isArrayOrListOrMap": false,
          "javaName": "port"
        },
        {
          "javaTypeName": "String",
          "fullQualifiedJavaTypeName": "java.lang.String",
          "isOptional": false,
          "isRefOnly": false,
          "isPayload": false,
          "isComplexType": false,
          "isEnum": false,
          "isString": true,
          "typeMirror": "java.lang.String",
          "isHttpCallback": false,
          "isArrayOrListOrMap": false,
          "javaName": "serverName"
        },
        {
          "javaTypeName": "String",
          "fullQualifiedJavaTypeName": "java.lang.String",
          "isOptional": false,
          "isRefOnly": false,
          "isPayload": false,
          "isComplexType": false,
          "isEnum": false,
          "isString": true,
          "typeMirror": "java.lang.String",
          "isHttpCallback": false,
          "isArrayOrListOrMap": false,
          "javaName": "username"
        },
        {
          "javaTypeName": "String",
          "fullQualifiedJavaTypeName": "java.lang.String",
          "isOptional": false,
          "isRefOnly": false,
          "isPayload": false,
          "isComplexType": false,
          "isEnum": false,
          "isString": true,
          "typeMirror": "java.lang.String",
          "isHttpCallback": false,
          "isArrayOrListOrMap": false,
          "javaName": "password"
        },
        {
          "javaTypeName": "String",
          "fullQualifiedJavaTypeName": "java.lang.String",
          "isOptional": true,
          "isRefOnly": false,
          "isPayload": false,
          "isComplexType": false,
          "isEnum": false,
          "isString": true,
          "typeMirror": "java.lang.String",
          "isHttpCallback": false,
          "isArrayOrListOrMap": false,
          "javaName": "keyStoreLocation"
        },
        {
          "javaTypeName": "String",
          "fullQualifiedJavaTypeName": "java.lang.String",
          "isOptional": true,
          "isRefOnly": false,
          "isPayload": false,
          "isComplexType": false,
          "isEnum": false,
          "isString": true,
          "typeMirror": "java.lang.String",
          "isHttpCallback": false,
          "isArrayOrListOrMap": false,
          "javaName": "keyStorePassword"
        }
      ],
      "javaName": "ConnectorConfig",
      "friendlyName": "Configuration",
      "type": "ConnectionManagementConfig"
    }
  ],
  "attributes": [],
  "processors": [
    {
      "isPaged": false,
      "isBatch": false,
      "samples": [],
      "javaReturnType": {
        "javaTypeName": "InputStream",
        "fullQualifiedJavaTypeName": "java.io.InputStream",
        "isOptional": false,
        "isRefOnly": false,
        "isPayload": false,
        "isComplexType": false,
        "isEnum": false,
        "isString": false,
        "isHttpCallback": false,
        "description": ""
      },
      "parameters": [
        {
          "javaTypeName": "String",
          "fullQualifiedJavaTypeName": "java.lang.String",
          "isOptional": false,
          "isRefOnly": false,
          "isPayload": false,
          "isComplexType": false,
          "isEnum": false,
          "isString": true,
          "typeMirror": "java.lang.String",
          "isHttpCallback": false,
          "isArrayOrListOrMap": false,
          "javaName": "channel"
        },
        {
          "javaTypeName": "String",
          "fullQualifiedJavaTypeName": "java.lang.String",
          "isOptional": false,
          "isRefOnly": false,
          "isPayload": false,
          "isComplexType": false,
          "isEnum": false,
          "isString": true,
          "typeMirror": "java.lang.String",
          "isHttpCallback": false,
          "isArrayOrListOrMap": false,
          "javaName": "requestContainer"
        },
        {
          "javaTypeName": "String",
          "fullQualifiedJavaTypeName": "java.lang.String",
          "isOptional": false,
          "isRefOnly": false,
          "isPayload": false,
          "isComplexType": false,
          "isEnum": false,
          "isString": true,
          "typeMirror": "java.lang.String",
          "isHttpCallback": false,
          "isArrayOrListOrMap": false,
          "javaName": "responseContainer"
        },
        {
          "javaTypeName": "String",
          "fullQualifiedJavaTypeName": "java.lang.String",
          "isOptional": false,
          "isRefOnly": false,
          "isPayload": false,
          "isComplexType": false,
          "isEnum": false,
          "isString": true,
          "typeMirror": "java.lang.String",
          "isHttpCallback": false,
          "isArrayOrListOrMap": false,
          "javaName": "errorContainer"
        },
        {
          "javaTypeName": "String",
          "fullQualifiedJavaTypeName": "java.lang.String",
          "isOptional": false,
          "isRefOnly": false,
          "isPayload": false,
          "isComplexType": false,
          "isEnum": false,
          "isString": true,
          "typeMirror": "java.lang.String",
          "isHttpCallback": false,
          "isArrayOrListOrMap": false,
          "javaName": "programName"
        },
        {
          "javaTypeName": "String",
          "fullQualifiedJavaTypeName": "java.lang.String",
          "isOptional": false,
          "isRefOnly": false,
          "isPayload": false,
          "isComplexType": false,
          "isEnum": false,
          "isString": true,
          "typeMirror": "java.lang.String",
          "isHttpCallback": false,
          "isArrayOrListOrMap": false,
          "javaName": "tpnName"
        },
        {
          "javaTypeName": "InputStream",
          "fullQualifiedJavaTypeName": "java.io.InputStream",
          "defaultValue": "#[payload]",
          "isOptional": true,
          "isRefOnly": false,
          "isPayload": false,
          "isComplexType": false,
          "isEnum": false,
          "isString": false,
          "typeMirror": "java.io.InputStream",
          "isHttpCallback": false,
          "isArrayOrListOrMap": false,
          "javaName": "payload"
        }
      ],
      "apiDocUrl": "",
      "javaName": "execute",
      "friendlyName": "Execute",
      "xsdName": "execute"
    }
  ],
  "filters": [],
  "transformers": [],
  "sources": [],
  "javaName": "CTGConnector",
  "friendlyName": "CTG",
  "xsdName": "ctg"
}